{
  "symbol": "ASPN",
  "timeframe": "5m",
  "source": "IBKR",
  "generated_at": "2026-05-07T11:17:33.274561",
  "bar_count": 280,
  "candles": [
    {
      "time": "2026-05-06T03:00:00",
      "open": 4.15,
      "high": 4.15,
      "low": 4.15,
      "close": 4.15,
      "volume": 1
    },
    {
      "time": "2026-05-06T03:05:00",
      "open": 4.15,
      "high": 4.15,
      "low": 4.15,
      "close": 4.15,
      "volume": 0
    },
    {
      "time": "2026-05-06T03:10:00",
      "open": 4.15,
      "high": 4.15,
      "low": 4.15,
      "close": 4.15,
      "volume": 0
    },
    {
      "time": "2026-05-06T03:15:00",
      "open": 4.15,
      "high": 4.15,
      "low": 4.15,
      "close": 4.15,
      "volume": 0
    },
    {
      "time": "2026-05-06T03:20:00",
      "open": 4.15,
      "high": 4.15,
      "low": 4.15,
      "close": 4.15,
      "volume": 0
    },
    {
      "time": "2026-05-06T03:25:00",
      "open": 4.15,
      "high": 4.15,
      "low": 4.15,
      "close": 4.15,
      "volume": 0
    },
    {
      "time": "2026-05-06T03:30:00",
      "open": 4.15,
      "high": 4.15,
      "low": 4.15,
      "close": 4.15,
      "volume": 0
    },
    {
      "time": "2026-05-06T03:35:00",
      "open": 4.15,
      "high": 4.15,
      "low": 4.15,
      "close": 4.15,
      "volume": 0
    },
    {
      "time": "2026-05-06T03:40:00",
      "open": 4.15,
      "high": 4.15,
      "low": 4.15,
      "close": 4.15,
      "volume": 0
    },
    {
      "time": "2026-05-06T03:45:00",
      "open": 4.15,
      "high": 4.15,
      "low": 4.15,
      "close": 4.15,
      "volume": 0
    },
    {
      "time": "2026-05-06T03:50:00",
      "open": 4.16,
      "high": 4.16,
      "low": 4.16,
      "close": 4.16,
      "volume": 13
    },
    {
      "time": "2026-05-06T03:55:00",
      "open": 4.16,
      "high": 4.16,
      "low": 4.16,
      "close": 4.16,
      "volume": 0
    },
    {
      "time": "2026-05-06T04:00:00",
      "open": 4.16,
      "high": 4.16,
      "low": 4.16,
      "close": 4.16,
      "volume": 0
    },
    {
      "time": "2026-05-06T04:05:00",
      "open": 4.16,
      "high": 4.16,
      "low": 4.16,
      "close": 4.16,
      "volume": 0
    },
    {
      "time": "2026-05-06T04:10:00",
      "open": 4.16,
      "high": 4.16,
      "low": 4.16,
      "close": 4.16,
      "volume": 0
    },
    {
      "time": "2026-05-06T04:15:00",
      "open": 4.16,
      "high": 4.16,
      "low": 4.16,
      "close": 4.16,
      "volume": 0
    },
    {
      "time": "2026-05-06T04:20:00",
      "open": 4.16,
      "high": 4.16,
      "low": 4.16,
      "close": 4.16,
      "volume": 0
    },
    {
      "time": "2026-05-06T04:25:00",
      "open": 4.16,
      "high": 4.16,
      "low": 4.16,
      "close": 4.16,
      "volume": 0
    },
    {
      "time": "2026-05-06T04:30:00",
      "open": 4.16,
      "high": 4.16,
      "low": 4.16,
      "close": 4.16,
      "volume": 0
    },
    {
      "time": "2026-05-06T04:35:00",
      "open": 4.16,
      "high": 4.16,
      "low": 4.16,
      "close": 4.16,
      "volume": 0
    },
    {
      "time": "2026-05-06T04:40:00",
      "open": 4.16,
      "high": 4.16,
      "low": 4.16,
      "close": 4.16,
      "volume": 0
    },
    {
      "time": "2026-05-06T04:45:00",
      "open": 4.16,
      "high": 4.16,
      "low": 4.16,
      "close": 4.16,
      "volume": 0
    },
    {
      "time": "2026-05-06T04:50:00",
      "open": 4.16,
      "high": 4.16,
      "low": 4.16,
      "close": 4.16,
      "volume": 0
    },
    {
      "time": "2026-05-06T04:55:00",
      "open": 4.16,
      "high": 4.16,
      "low": 4.16,
      "close": 4.16,
      "volume": 0
    },
    {
      "time": "2026-05-06T05:00:00",
      "open": 4.16,
      "high": 4.16,
      "low": 4.16,
      "close": 4.16,
      "volume": 0
    },
    {
      "time": "2026-05-06T05:05:00",
      "open": 4.16,
      "high": 4.16,
      "low": 4.16,
      "close": 4.16,
      "volume": 0
    },
    {
      "time": "2026-05-06T05:10:00",
      "open": 4.19,
      "high": 4.19,
      "low": 4.19,
      "close": 4.19,
      "volume": 1
    },
    {
      "time": "2026-05-06T05:15:00",
      "open": 4.19,
      "high": 4.19,
      "low": 4.19,
      "close": 4.19,
      "volume": 0
    },
    {
      "time": "2026-05-06T05:20:00",
      "open": 4.19,
      "high": 4.19,
      "low": 4.19,
      "close": 4.19,
      "volume": 0
    },
    {
      "time": "2026-05-06T05:25:00",
      "open": 4.19,
      "high": 4.19,
      "low": 4.19,
      "close": 4.19,
      "volume": 0
    },
    {
      "time": "2026-05-06T05:30:00",
      "open": 4.19,
      "high": 4.19,
      "low": 4.19,
      "close": 4.19,
      "volume": 0
    },
    {
      "time": "2026-05-06T05:35:00",
      "open": 4.19,
      "high": 4.19,
      "low": 4.19,
      "close": 4.19,
      "volume": 0
    },
    {
      "time": "2026-05-06T05:40:00",
      "open": 4.19,
      "high": 4.19,
      "low": 4.19,
      "close": 4.19,
      "volume": 0
    },
    {
      "time": "2026-05-06T05:45:00",
      "open": 4.19,
      "high": 4.19,
      "low": 4.19,
      "close": 4.19,
      "volume": 0
    },
    {
      "time": "2026-05-06T05:50:00",
      "open": 4.19,
      "high": 4.19,
      "low": 4.19,
      "close": 4.19,
      "volume": 0
    },
    {
      "time": "2026-05-06T05:55:00",
      "open": 4.19,
      "high": 4.19,
      "low": 4.19,
      "close": 4.19,
      "volume": 0
    },
    {
      "time": "2026-05-06T06:00:00",
      "open": 4.205,
      "high": 4.23,
      "low": 4.205,
      "close": 4.23,
      "volume": 12
    },
    {
      "time": "2026-05-06T06:05:00",
      "open": 4.23,
      "high": 4.23,
      "low": 4.23,
      "close": 4.23,
      "volume": 0
    },
    {
      "time": "2026-05-06T06:10:00",
      "open": 4.243,
      "high": 4.243,
      "low": 4.24,
      "close": 4.24,
      "volume": 11
    },
    {
      "time": "2026-05-06T06:15:00",
      "open": 4.24,
      "high": 4.24,
      "low": 4.24,
      "close": 4.24,
      "volume": 0
    },
    {
      "time": "2026-05-06T06:20:00",
      "open": 4.22,
      "high": 4.22,
      "low": 4.22,
      "close": 4.22,
      "volume": 5
    },
    {
      "time": "2026-05-06T06:25:00",
      "open": 4.22,
      "high": 4.22,
      "low": 4.22,
      "close": 4.22,
      "volume": 24
    },
    {
      "time": "2026-05-06T06:30:00",
      "open": 4.22,
      "high": 4.22,
      "low": 4.22,
      "close": 4.22,
      "volume": 0
    },
    {
      "time": "2026-05-06T06:35:00",
      "open": 4.22,
      "high": 4.22,
      "low": 4.22,
      "close": 4.22,
      "volume": 0
    },
    {
      "time": "2026-05-06T06:40:00",
      "open": 4.22,
      "high": 4.22,
      "low": 4.22,
      "close": 4.22,
      "volume": 0
    },
    {
      "time": "2026-05-06T06:45:00",
      "open": 4.22,
      "high": 4.22,
      "low": 4.22,
      "close": 4.22,
      "volume": 0
    },
    {
      "time": "2026-05-06T06:50:00",
      "open": 4.22,
      "high": 4.22,
      "low": 4.22,
      "close": 4.22,
      "volume": 0
    },
    {
      "time": "2026-05-06T06:55:00",
      "open": 4.21,
      "high": 4.2135,
      "low": 4.17,
      "close": 4.17,
      "volume": 101
    },
    {
      "time": "2026-05-06T07:00:00",
      "open": 4.17,
      "high": 4.17,
      "low": 4.17,
      "close": 4.17,
      "volume": 0
    },
    {
      "time": "2026-05-06T07:05:00",
      "open": 4.17,
      "high": 4.17,
      "low": 4.17,
      "close": 4.17,
      "volume": 0
    },
    {
      "time": "2026-05-06T07:10:00",
      "open": 4.1765,
      "high": 4.185,
      "low": 4.1765,
      "close": 4.185,
      "volume": 7
    },
    {
      "time": "2026-05-06T07:15:00",
      "open": 4.185,
      "high": 4.185,
      "low": 4.185,
      "close": 4.185,
      "volume": 0
    },
    {
      "time": "2026-05-06T07:20:00",
      "open": 4.185,
      "high": 4.185,
      "low": 4.185,
      "close": 4.185,
      "volume": 0
    },
    {
      "time": "2026-05-06T07:25:00",
      "open": 4.185,
      "high": 4.185,
      "low": 4.185,
      "close": 4.185,
      "volume": 0
    },
    {
      "time": "2026-05-06T07:30:00",
      "open": 4.185,
      "high": 4.185,
      "low": 4.185,
      "close": 4.185,
      "volume": 0
    },
    {
      "time": "2026-05-06T07:35:00",
      "open": 4.185,
      "high": 4.185,
      "low": 4.185,
      "close": 4.185,
      "volume": 0
    },
    {
      "time": "2026-05-06T07:40:00",
      "open": 4.185,
      "high": 4.185,
      "low": 4.185,
      "close": 4.185,
      "volume": 0
    },
    {
      "time": "2026-05-06T07:45:00",
      "open": 4.185,
      "high": 4.185,
      "low": 4.185,
      "close": 4.185,
      "volume": 0
    },
    {
      "time": "2026-05-06T07:50:00",
      "open": 4.185,
      "high": 4.185,
      "low": 4.185,
      "close": 4.185,
      "volume": 0
    },
    {
      "time": "2026-05-06T07:55:00",
      "open": 4.185,
      "high": 4.185,
      "low": 4.185,
      "close": 4.185,
      "volume": 0
    },
    {
      "time": "2026-05-06T08:00:00",
      "open": 4.185,
      "high": 4.185,
      "low": 4.185,
      "close": 4.185,
      "volume": 0
    },
    {
      "time": "2026-05-06T08:05:00",
      "open": 4.185,
      "high": 4.185,
      "low": 4.185,
      "close": 4.185,
      "volume": 0
    },
    {
      "time": "2026-05-06T08:10:00",
      "open": 4.175,
      "high": 4.175,
      "low": 4.175,
      "close": 4.175,
      "volume": 5
    },
    {
      "time": "2026-05-06T08:15:00",
      "open": 4.175,
      "high": 4.175,
      "low": 4.175,
      "close": 4.175,
      "volume": 0
    },
    {
      "time": "2026-05-06T08:20:00",
      "open": 4.175,
      "high": 4.175,
      "low": 4.175,
      "close": 4.175,
      "volume": 0
    },
    {
      "time": "2026-05-06T08:25:00",
      "open": 4.175,
      "high": 4.175,
      "low": 4.175,
      "close": 4.175,
      "volume": 0
    },
    {
      "time": "2026-05-06T08:30:00",
      "open": 4.15,
      "high": 4.155,
      "low": 4.14,
      "close": 4.145,
      "volume": 326
    },
    {
      "time": "2026-05-06T08:35:00",
      "open": 4.15,
      "high": 4.1868,
      "low": 4.135,
      "close": 4.14,
      "volume": 138
    },
    {
      "time": "2026-05-06T08:40:00",
      "open": 4.14,
      "high": 4.14,
      "low": 4.09,
      "close": 4.09,
      "volume": 230
    },
    {
      "time": "2026-05-06T08:45:00",
      "open": 4.095,
      "high": 4.1098,
      "low": 4.085,
      "close": 4.105,
      "volume": 162
    },
    {
      "time": "2026-05-06T08:50:00",
      "open": 4.1,
      "high": 4.115,
      "low": 4.09,
      "close": 4.09,
      "volume": 115
    },
    {
      "time": "2026-05-06T08:55:00",
      "open": 4.1,
      "high": 4.12,
      "low": 4.04,
      "close": 4.045,
      "volume": 247
    },
    {
      "time": "2026-05-06T09:00:00",
      "open": 4.05,
      "high": 4.05,
      "low": 4.0212,
      "close": 4.035,
      "volume": 227
    },
    {
      "time": "2026-05-06T09:05:00",
      "open": 4.025,
      "high": 4.045,
      "low": 4.02,
      "close": 4.025,
      "volume": 319
    },
    {
      "time": "2026-05-06T09:10:00",
      "open": 4.03,
      "high": 4.05,
      "low": 4.02,
      "close": 4.05,
      "volume": 257
    },
    {
      "time": "2026-05-06T09:15:00",
      "open": 4.04,
      "high": 4.05,
      "low": 4.0343,
      "close": 4.05,
      "volume": 143
    },
    {
      "time": "2026-05-06T09:20:00",
      "open": 4.05,
      "high": 4.06,
      "low": 4.045,
      "close": 4.06,
      "volume": 126
    },
    {
      "time": "2026-05-06T09:25:00",
      "open": 4.06,
      "high": 4.07,
      "low": 4.04,
      "close": 4.04,
      "volume": 150
    },
    {
      "time": "2026-05-06T09:30:00",
      "open": 4.035,
      "high": 4.055,
      "low": 4.035,
      "close": 4.055,
      "volume": 51
    },
    {
      "time": "2026-05-06T09:35:00",
      "open": 4.055,
      "high": 4.0577,
      "low": 4.04,
      "close": 4.045,
      "volume": 50
    },
    {
      "time": "2026-05-06T09:40:00",
      "open": 4.045,
      "high": 4.05,
      "low": 4.025,
      "close": 4.045,
      "volume": 247
    },
    {
      "time": "2026-05-06T09:45:00",
      "open": 4.045,
      "high": 4.045,
      "low": 4.0402,
      "close": 4.045,
      "volume": 29
    },
    {
      "time": "2026-05-06T09:50:00",
      "open": 4.045,
      "high": 4.08,
      "low": 4.04,
      "close": 4.08,
      "volume": 345
    },
    {
      "time": "2026-05-06T09:55:00",
      "open": 4.08,
      "high": 4.085,
      "low": 4.045,
      "close": 4.045,
      "volume": 289
    },
    {
      "time": "2026-05-06T10:00:00",
      "open": 4.0498,
      "high": 4.0498,
      "low": 4.035,
      "close": 4.035,
      "volume": 35
    },
    {
      "time": "2026-05-06T10:05:00",
      "open": 4.035,
      "high": 4.07,
      "low": 4.035,
      "close": 4.06,
      "volume": 195
    },
    {
      "time": "2026-05-06T10:10:00",
      "open": 4.065,
      "high": 4.065,
      "low": 4.06,
      "close": 4.06,
      "volume": 55
    },
    {
      "time": "2026-05-06T10:15:00",
      "open": 4.0599,
      "high": 4.075,
      "low": 4.0501,
      "close": 4.065,
      "volume": 190
    },
    {
      "time": "2026-05-06T10:20:00",
      "open": 4.065,
      "high": 4.07,
      "low": 4.045,
      "close": 4.045,
      "volume": 68
    },
    {
      "time": "2026-05-06T10:25:00",
      "open": 4.045,
      "high": 4.065,
      "low": 4.045,
      "close": 4.065,
      "volume": 67
    },
    {
      "time": "2026-05-06T10:30:00",
      "open": 4.065,
      "high": 4.065,
      "low": 4.06,
      "close": 4.065,
      "volume": 10
    },
    {
      "time": "2026-05-06T10:35:00",
      "open": 4.065,
      "high": 4.085,
      "low": 4.065,
      "close": 4.085,
      "volume": 34
    },
    {
      "time": "2026-05-06T10:40:00",
      "open": 4.085,
      "high": 4.09,
      "low": 4.07,
      "close": 4.075,
      "volume": 131
    },
    {
      "time": "2026-05-06T10:45:00",
      "open": 4.075,
      "high": 4.075,
      "low": 4.04,
      "close": 4.045,
      "volume": 230
    },
    {
      "time": "2026-05-06T10:50:00",
      "open": 4.045,
      "high": 4.055,
      "low": 4.04,
      "close": 4.05,
      "volume": 134
    },
    {
      "time": "2026-05-06T10:55:00",
      "open": 4.06,
      "high": 4.085,
      "low": 4.06,
      "close": 4.07,
      "volume": 184
    },
    {
      "time": "2026-05-06T11:00:00",
      "open": 4.075,
      "high": 4.075,
      "low": 4.065,
      "close": 4.075,
      "volume": 67
    },
    {
      "time": "2026-05-06T11:05:00",
      "open": 4.075,
      "high": 4.075,
      "low": 4.065,
      "close": 4.065,
      "volume": 40
    },
    {
      "time": "2026-05-06T11:10:00",
      "open": 4.065,
      "high": 4.065,
      "low": 4.06,
      "close": 4.065,
      "volume": 61
    },
    {
      "time": "2026-05-06T11:15:00",
      "open": 4.065,
      "high": 4.065,
      "low": 4.055,
      "close": 4.055,
      "volume": 43
    },
    {
      "time": "2026-05-06T11:20:00",
      "open": 4.051,
      "high": 4.065,
      "low": 4.05,
      "close": 4.06,
      "volume": 205
    },
    {
      "time": "2026-05-06T11:25:00",
      "open": 4.065,
      "high": 4.085,
      "low": 4.065,
      "close": 4.085,
      "volume": 58
    },
    {
      "time": "2026-05-06T11:30:00",
      "open": 4.085,
      "high": 4.085,
      "low": 4.075,
      "close": 4.085,
      "volume": 114
    },
    {
      "time": "2026-05-06T11:35:00",
      "open": 4.08,
      "high": 4.08,
      "low": 4.035,
      "close": 4.035,
      "volume": 257
    },
    {
      "time": "2026-05-06T11:40:00",
      "open": 4.035,
      "high": 4.045,
      "low": 4.03,
      "close": 4.035,
      "volume": 187
    },
    {
      "time": "2026-05-06T11:45:00",
      "open": 4.03,
      "high": 4.035,
      "low": 4.025,
      "close": 4.035,
      "volume": 408
    },
    {
      "time": "2026-05-06T11:50:00",
      "open": 4.03,
      "high": 4.045,
      "low": 4.03,
      "close": 4.04,
      "volume": 67
    },
    {
      "time": "2026-05-06T11:55:00",
      "open": 4.045,
      "high": 4.06,
      "low": 4.045,
      "close": 4.055,
      "volume": 119
    },
    {
      "time": "2026-05-06T12:00:00",
      "open": 4.055,
      "high": 4.07,
      "low": 4.055,
      "close": 4.07,
      "volume": 62
    },
    {
      "time": "2026-05-06T12:05:00",
      "open": 4.065,
      "high": 4.07,
      "low": 4.06,
      "close": 4.065,
      "volume": 29
    },
    {
      "time": "2026-05-06T12:10:00",
      "open": 4.07,
      "high": 4.105,
      "low": 4.07,
      "close": 4.085,
      "volume": 367
    },
    {
      "time": "2026-05-06T12:15:00",
      "open": 4.085,
      "high": 4.085,
      "low": 4.06,
      "close": 4.06,
      "volume": 158
    },
    {
      "time": "2026-05-06T12:20:00",
      "open": 4.065,
      "high": 4.07,
      "low": 4.055,
      "close": 4.065,
      "volume": 163
    },
    {
      "time": "2026-05-06T12:25:00",
      "open": 4.065,
      "high": 4.08,
      "low": 4.065,
      "close": 4.075,
      "volume": 25
    },
    {
      "time": "2026-05-06T12:30:00",
      "open": 4.075,
      "high": 4.085,
      "low": 4.075,
      "close": 4.085,
      "volume": 82
    },
    {
      "time": "2026-05-06T12:35:00",
      "open": 4.08,
      "high": 4.12,
      "low": 4.08,
      "close": 4.115,
      "volume": 173
    },
    {
      "time": "2026-05-06T12:40:00",
      "open": 4.115,
      "high": 4.115,
      "low": 4.09,
      "close": 4.105,
      "volume": 178
    },
    {
      "time": "2026-05-06T12:45:00",
      "open": 4.1089,
      "high": 4.115,
      "low": 4.105,
      "close": 4.115,
      "volume": 51
    },
    {
      "time": "2026-05-06T12:50:00",
      "open": 4.11,
      "high": 4.11,
      "low": 4.1,
      "close": 4.105,
      "volume": 93
    },
    {
      "time": "2026-05-06T12:55:00",
      "open": 4.105,
      "high": 4.11,
      "low": 4.105,
      "close": 4.105,
      "volume": 24
    },
    {
      "time": "2026-05-06T13:00:00",
      "open": 4.105,
      "high": 4.1074,
      "low": 4.1,
      "close": 4.1074,
      "volume": 51
    },
    {
      "time": "2026-05-06T13:05:00",
      "open": 4.105,
      "high": 4.12,
      "low": 4.105,
      "close": 4.115,
      "volume": 87
    },
    {
      "time": "2026-05-06T13:10:00",
      "open": 4.115,
      "high": 4.135,
      "low": 4.11,
      "close": 4.13,
      "volume": 294
    },
    {
      "time": "2026-05-06T13:15:00",
      "open": 4.125,
      "high": 4.13,
      "low": 4.12,
      "close": 4.13,
      "volume": 44
    },
    {
      "time": "2026-05-06T13:20:00",
      "open": 4.125,
      "high": 4.13,
      "low": 4.12,
      "close": 4.125,
      "volume": 38
    },
    {
      "time": "2026-05-06T13:25:00",
      "open": 4.125,
      "high": 4.14,
      "low": 4.125,
      "close": 4.13,
      "volume": 69
    },
    {
      "time": "2026-05-06T13:30:00",
      "open": 4.135,
      "high": 4.14,
      "low": 4.12,
      "close": 4.125,
      "volume": 142
    },
    {
      "time": "2026-05-06T13:35:00",
      "open": 4.125,
      "high": 4.155,
      "low": 4.105,
      "close": 4.105,
      "volume": 575
    },
    {
      "time": "2026-05-06T13:40:00",
      "open": 4.105,
      "high": 4.11,
      "low": 4.1,
      "close": 4.105,
      "volume": 71
    },
    {
      "time": "2026-05-06T13:45:00",
      "open": 4.105,
      "high": 4.13,
      "low": 4.105,
      "close": 4.125,
      "volume": 224
    },
    {
      "time": "2026-05-06T13:50:00",
      "open": 4.125,
      "high": 4.16,
      "low": 4.125,
      "close": 4.155,
      "volume": 328
    },
    {
      "time": "2026-05-06T13:55:00",
      "open": 4.16,
      "high": 4.17,
      "low": 4.16,
      "close": 4.165,
      "volume": 150
    },
    {
      "time": "2026-05-06T14:00:00",
      "open": 4.17,
      "high": 4.17,
      "low": 4.145,
      "close": 4.155,
      "volume": 354
    },
    {
      "time": "2026-05-06T14:05:00",
      "open": 4.1513,
      "high": 4.16,
      "low": 4.115,
      "close": 4.13,
      "volume": 711
    },
    {
      "time": "2026-05-06T14:10:00",
      "open": 4.135,
      "high": 4.135,
      "low": 4.11,
      "close": 4.115,
      "volume": 125
    },
    {
      "time": "2026-05-06T14:15:00",
      "open": 4.115,
      "high": 4.15,
      "low": 4.115,
      "close": 4.145,
      "volume": 175
    },
    {
      "time": "2026-05-06T14:20:00",
      "open": 4.145,
      "high": 4.15,
      "low": 4.13,
      "close": 4.145,
      "volume": 288
    },
    {
      "time": "2026-05-06T14:25:00",
      "open": 4.145,
      "high": 4.15,
      "low": 4.14,
      "close": 4.145,
      "volume": 113
    },
    {
      "time": "2026-05-06T14:30:00",
      "open": 4.145,
      "high": 4.145,
      "low": 4.125,
      "close": 4.135,
      "volume": 351
    },
    {
      "time": "2026-05-06T14:35:00",
      "open": 4.14,
      "high": 4.14,
      "low": 4.1,
      "close": 4.11,
      "volume": 377
    },
    {
      "time": "2026-05-06T14:40:00",
      "open": 4.105,
      "high": 4.12,
      "low": 4.095,
      "close": 4.115,
      "volume": 311
    },
    {
      "time": "2026-05-06T14:45:00",
      "open": 4.115,
      "high": 4.115,
      "low": 4.065,
      "close": 4.065,
      "volume": 548
    },
    {
      "time": "2026-05-06T14:50:00",
      "open": 4.065,
      "high": 4.09,
      "low": 4.06,
      "close": 4.085,
      "volume": 756
    },
    {
      "time": "2026-05-06T14:55:00",
      "open": 4.08,
      "high": 4.12,
      "low": 4.075,
      "close": 4.12,
      "volume": 915
    },
    {
      "time": "2026-05-06T15:00:00",
      "open": 4.115,
      "high": 4.12,
      "low": 4.115,
      "close": 4.12,
      "volume": 805
    },
    {
      "time": "2026-05-06T15:05:00",
      "open": 4.12,
      "high": 4.12,
      "low": 4.12,
      "close": 4.12,
      "volume": 0
    },
    {
      "time": "2026-05-06T15:10:00",
      "open": 4.12,
      "high": 4.12,
      "low": 4.12,
      "close": 4.12,
      "volume": 0
    },
    {
      "time": "2026-05-06T15:15:00",
      "open": 4.12,
      "high": 4.12,
      "low": 4.12,
      "close": 4.12,
      "volume": 0
    },
    {
      "time": "2026-05-06T15:20:00",
      "open": 4.12,
      "high": 4.12,
      "low": 4.12,
      "close": 4.12,
      "volume": 0
    },
    {
      "time": "2026-05-06T15:25:00",
      "open": 4.12,
      "high": 4.12,
      "low": 4.12,
      "close": 4.12,
      "volume": 0
    },
    {
      "time": "2026-05-06T15:30:00",
      "open": 4.12,
      "high": 4.12,
      "low": 4.12,
      "close": 4.12,
      "volume": 0
    },
    {
      "time": "2026-05-06T15:35:00",
      "open": 4.12,
      "high": 4.12,
      "low": 4.12,
      "close": 4.12,
      "volume": 0
    },
    {
      "time": "2026-05-06T15:40:00",
      "open": 4.12,
      "high": 4.12,
      "low": 4.12,
      "close": 4.12,
      "volume": 0
    },
    {
      "time": "2026-05-06T15:45:00",
      "open": 4.12,
      "high": 4.12,
      "low": 4.12,
      "close": 4.12,
      "volume": 0
    },
    {
      "time": "2026-05-06T15:50:00",
      "open": 4.12,
      "high": 4.12,
      "low": 4.12,
      "close": 4.12,
      "volume": 0
    },
    {
      "time": "2026-05-06T15:55:00",
      "open": 4.12,
      "high": 4.12,
      "low": 4.12,
      "close": 4.12,
      "volume": 0
    },
    {
      "time": "2026-05-06T16:00:00",
      "open": 4.12,
      "high": 4.12,
      "low": 4.12,
      "close": 4.12,
      "volume": 0
    },
    {
      "time": "2026-05-06T16:05:00",
      "open": 4.12,
      "high": 4.12,
      "low": 4.12,
      "close": 4.12,
      "volume": 0
    },
    {
      "time": "2026-05-06T16:10:00",
      "open": 4.12,
      "high": 4.12,
      "low": 4.12,
      "close": 4.12,
      "volume": 0
    },
    {
      "time": "2026-05-06T16:15:00",
      "open": 4.12,
      "high": 4.12,
      "low": 4.12,
      "close": 4.12,
      "volume": 0
    },
    {
      "time": "2026-05-06T16:20:00",
      "open": 4.12,
      "high": 4.12,
      "low": 4.12,
      "close": 4.12,
      "volume": 0
    },
    {
      "time": "2026-05-06T16:25:00",
      "open": 4.12,
      "high": 4.12,
      "low": 4.12,
      "close": 4.12,
      "volume": 0
    },
    {
      "time": "2026-05-06T16:30:00",
      "open": 4.12,
      "high": 4.12,
      "low": 4.12,
      "close": 4.12,
      "volume": 0
    },
    {
      "time": "2026-05-06T16:35:00",
      "open": 4.12,
      "high": 4.12,
      "low": 4.12,
      "close": 4.12,
      "volume": 0
    },
    {
      "time": "2026-05-06T16:40:00",
      "open": 4.12,
      "high": 4.12,
      "low": 4.12,
      "close": 4.12,
      "volume": 0
    },
    {
      "time": "2026-05-06T16:45:00",
      "open": 4.12,
      "high": 4.12,
      "low": 4.12,
      "close": 4.12,
      "volume": 0
    },
    {
      "time": "2026-05-06T16:50:00",
      "open": 4.12,
      "high": 4.12,
      "low": 4.12,
      "close": 4.12,
      "volume": 0
    },
    {
      "time": "2026-05-06T16:55:00",
      "open": 4.12,
      "high": 4.12,
      "low": 4.12,
      "close": 4.12,
      "volume": 0
    },
    {
      "time": "2026-05-06T17:00:00",
      "open": 4.12,
      "high": 4.12,
      "low": 4.12,
      "close": 4.12,
      "volume": 0
    },
    {
      "time": "2026-05-06T17:05:00",
      "open": 4.12,
      "high": 4.12,
      "low": 4.12,
      "close": 4.12,
      "volume": 0
    },
    {
      "time": "2026-05-06T17:10:00",
      "open": 4.12,
      "high": 4.12,
      "low": 4.12,
      "close": 4.12,
      "volume": 0
    },
    {
      "time": "2026-05-06T17:15:00",
      "open": 4.12,
      "high": 4.12,
      "low": 4.12,
      "close": 4.12,
      "volume": 0
    },
    {
      "time": "2026-05-06T17:20:00",
      "open": 4.14,
      "high": 4.14,
      "low": 4.14,
      "close": 4.14,
      "volume": 9
    },
    {
      "time": "2026-05-06T17:25:00",
      "open": 4.14,
      "high": 4.14,
      "low": 4.14,
      "close": 4.14,
      "volume": 0
    },
    {
      "time": "2026-05-06T17:30:00",
      "open": 4.14,
      "high": 4.14,
      "low": 4.14,
      "close": 4.14,
      "volume": 0
    },
    {
      "time": "2026-05-06T17:35:00",
      "open": 4.14,
      "high": 4.14,
      "low": 4.14,
      "close": 4.14,
      "volume": 0
    },
    {
      "time": "2026-05-06T17:40:00",
      "open": 4.14,
      "high": 4.14,
      "low": 4.14,
      "close": 4.14,
      "volume": 0
    },
    {
      "time": "2026-05-06T17:45:00",
      "open": 4.14,
      "high": 4.14,
      "low": 4.14,
      "close": 4.14,
      "volume": 0
    },
    {
      "time": "2026-05-06T17:50:00",
      "open": 4.14,
      "high": 4.14,
      "low": 4.14,
      "close": 4.14,
      "volume": 0
    },
    {
      "time": "2026-05-06T17:55:00",
      "open": 4.14,
      "high": 4.14,
      "low": 4.14,
      "close": 4.14,
      "volume": 0
    },
    {
      "time": "2026-05-06T18:00:00",
      "open": 4.14,
      "high": 4.14,
      "low": 4.14,
      "close": 4.14,
      "volume": 0
    },
    {
      "time": "2026-05-06T18:05:00",
      "open": 4.14,
      "high": 4.14,
      "low": 4.14,
      "close": 4.14,
      "volume": 0
    },
    {
      "time": "2026-05-06T18:10:00",
      "open": 4.14,
      "high": 4.14,
      "low": 4.14,
      "close": 4.14,
      "volume": 0
    },
    {
      "time": "2026-05-06T18:15:00",
      "open": 4.14,
      "high": 4.14,
      "low": 4.14,
      "close": 4.14,
      "volume": 0
    },
    {
      "time": "2026-05-06T18:20:00",
      "open": 4.14,
      "high": 4.14,
      "low": 4.14,
      "close": 4.14,
      "volume": 0
    },
    {
      "time": "2026-05-06T18:25:00",
      "open": 4.14,
      "high": 4.14,
      "low": 4.14,
      "close": 4.14,
      "volume": 0
    },
    {
      "time": "2026-05-06T18:30:00",
      "open": 4.14,
      "high": 4.14,
      "low": 4.14,
      "close": 4.14,
      "volume": 0
    },
    {
      "time": "2026-05-06T18:35:00",
      "open": 4.14,
      "high": 4.14,
      "low": 4.14,
      "close": 4.14,
      "volume": 0
    },
    {
      "time": "2026-05-06T18:40:00",
      "open": 4.08,
      "high": 4.08,
      "low": 4.08,
      "close": 4.08,
      "volume": 5
    },
    {
      "time": "2026-05-06T18:45:00",
      "open": 4.08,
      "high": 4.08,
      "low": 4.08,
      "close": 4.08,
      "volume": 0
    },
    {
      "time": "2026-05-06T18:50:00",
      "open": 4.08,
      "high": 4.08,
      "low": 4.08,
      "close": 4.08,
      "volume": 0
    },
    {
      "time": "2026-05-06T18:55:00",
      "open": 4.08,
      "high": 4.08,
      "low": 4.08,
      "close": 4.08,
      "volume": 0
    },
    {
      "time": "2026-05-07T03:00:00",
      "open": 4.08,
      "high": 4.12,
      "low": 4.08,
      "close": 4.12,
      "volume": 7
    },
    {
      "time": "2026-05-07T03:05:00",
      "open": 4.12,
      "high": 4.12,
      "low": 4.12,
      "close": 4.12,
      "volume": 0
    },
    {
      "time": "2026-05-07T03:10:00",
      "open": 4.12,
      "high": 4.12,
      "low": 4.12,
      "close": 4.12,
      "volume": 0
    },
    {
      "time": "2026-05-07T03:15:00",
      "open": 4.12,
      "high": 4.12,
      "low": 4.12,
      "close": 4.12,
      "volume": 0
    },
    {
      "time": "2026-05-07T03:20:00",
      "open": 4.12,
      "high": 4.12,
      "low": 4.12,
      "close": 4.12,
      "volume": 0
    },
    {
      "time": "2026-05-07T03:25:00",
      "open": 4.12,
      "high": 4.12,
      "low": 4.12,
      "close": 4.12,
      "volume": 0
    },
    {
      "time": "2026-05-07T03:30:00",
      "open": 4.12,
      "high": 4.12,
      "low": 4.12,
      "close": 4.12,
      "volume": 0
    },
    {
      "time": "2026-05-07T03:35:00",
      "open": 4.12,
      "high": 4.12,
      "low": 4.12,
      "close": 4.12,
      "volume": 0
    },
    {
      "time": "2026-05-07T03:40:00",
      "open": 4.12,
      "high": 4.12,
      "low": 4.12,
      "close": 4.12,
      "volume": 0
    },
    {
      "time": "2026-05-07T03:45:00",
      "open": 4.12,
      "high": 4.12,
      "low": 4.12,
      "close": 4.12,
      "volume": 0
    },
    {
      "time": "2026-05-07T03:50:00",
      "open": 4.12,
      "high": 4.12,
      "low": 4.12,
      "close": 4.12,
      "volume": 0
    },
    {
      "time": "2026-05-07T03:55:00",
      "open": 4.12,
      "high": 4.12,
      "low": 4.12,
      "close": 4.12,
      "volume": 0
    },
    {
      "time": "2026-05-07T04:00:00",
      "open": 4.12,
      "high": 4.12,
      "low": 4.12,
      "close": 4.12,
      "volume": 0
    },
    {
      "time": "2026-05-07T04:05:00",
      "open": 4.12,
      "high": 4.12,
      "low": 4.12,
      "close": 4.12,
      "volume": 0
    },
    {
      "time": "2026-05-07T04:10:00",
      "open": 4.12,
      "high": 4.12,
      "low": 4.12,
      "close": 4.12,
      "volume": 0
    },
    {
      "time": "2026-05-07T04:15:00",
      "open": 4.12,
      "high": 4.12,
      "low": 4.12,
      "close": 4.12,
      "volume": 0
    },
    {
      "time": "2026-05-07T04:20:00",
      "open": 4.12,
      "high": 4.12,
      "low": 4.12,
      "close": 4.12,
      "volume": 0
    },
    {
      "time": "2026-05-07T04:25:00",
      "open": 4.12,
      "high": 4.12,
      "low": 4.12,
      "close": 4.12,
      "volume": 0
    },
    {
      "time": "2026-05-07T04:30:00",
      "open": 4.12,
      "high": 4.12,
      "low": 4.12,
      "close": 4.12,
      "volume": 0
    },
    {
      "time": "2026-05-07T04:35:00",
      "open": 4.12,
      "high": 4.12,
      "low": 4.12,
      "close": 4.12,
      "volume": 0
    },
    {
      "time": "2026-05-07T04:40:00",
      "open": 4.12,
      "high": 4.12,
      "low": 4.12,
      "close": 4.12,
      "volume": 0
    },
    {
      "time": "2026-05-07T04:45:00",
      "open": 4.12,
      "high": 4.12,
      "low": 4.12,
      "close": 4.12,
      "volume": 0
    },
    {
      "time": "2026-05-07T04:50:00",
      "open": 4.12,
      "high": 4.12,
      "low": 4.12,
      "close": 4.12,
      "volume": 0
    },
    {
      "time": "2026-05-07T04:55:00",
      "open": 4.12,
      "high": 4.12,
      "low": 4.12,
      "close": 4.12,
      "volume": 0
    },
    {
      "time": "2026-05-07T05:00:00",
      "open": 4.12,
      "high": 4.12,
      "low": 4.12,
      "close": 4.12,
      "volume": 0
    },
    {
      "time": "2026-05-07T05:05:00",
      "open": 4.12,
      "high": 4.12,
      "low": 4.12,
      "close": 4.12,
      "volume": 0
    },
    {
      "time": "2026-05-07T05:10:00",
      "open": 4.12,
      "high": 4.12,
      "low": 4.12,
      "close": 4.12,
      "volume": 0
    },
    {
      "time": "2026-05-07T05:15:00",
      "open": 4.12,
      "high": 4.12,
      "low": 4.12,
      "close": 4.12,
      "volume": 0
    },
    {
      "time": "2026-05-07T05:20:00",
      "open": 4.12,
      "high": 4.12,
      "low": 4.12,
      "close": 4.12,
      "volume": 0
    },
    {
      "time": "2026-05-07T05:25:00",
      "open": 4.12,
      "high": 4.12,
      "low": 4.12,
      "close": 4.12,
      "volume": 0
    },
    {
      "time": "2026-05-07T05:30:00",
      "open": 4.21,
      "high": 4.6,
      "low": 4.21,
      "close": 4.6,
      "volume": 114
    },
    {
      "time": "2026-05-07T05:35:00",
      "open": 4.6,
      "high": 4.6,
      "low": 4.6,
      "close": 4.6,
      "volume": 0
    },
    {
      "time": "2026-05-07T05:40:00",
      "open": 4.62,
      "high": 4.69,
      "low": 4.48,
      "close": 4.48,
      "volume": 58
    },
    {
      "time": "2026-05-07T05:45:00",
      "open": 4.495,
      "high": 4.53,
      "low": 4.33,
      "close": 4.47,
      "volume": 18
    },
    {
      "time": "2026-05-07T05:50:00",
      "open": 4.479,
      "high": 4.479,
      "low": 4.479,
      "close": 4.479,
      "volume": 1
    },
    {
      "time": "2026-05-07T05:55:00",
      "open": 4.46,
      "high": 4.46,
      "low": 4.46,
      "close": 4.46,
      "volume": 11
    },
    {
      "time": "2026-05-07T06:00:00",
      "open": 4.47,
      "high": 4.47,
      "low": 4.46,
      "close": 4.46,
      "volume": 14
    },
    {
      "time": "2026-05-07T06:05:00",
      "open": 4.46,
      "high": 4.46,
      "low": 4.46,
      "close": 4.46,
      "volume": 2
    },
    {
      "time": "2026-05-07T06:10:00",
      "open": 4.46,
      "high": 4.46,
      "low": 4.29,
      "close": 4.29,
      "volume": 7
    },
    {
      "time": "2026-05-07T06:15:00",
      "open": 4.33,
      "high": 4.34,
      "low": 4.3,
      "close": 4.3285,
      "volume": 43
    },
    {
      "time": "2026-05-07T06:20:00",
      "open": 4.29,
      "high": 4.4,
      "low": 4.29,
      "close": 4.4,
      "volume": 86
    },
    {
      "time": "2026-05-07T06:25:00",
      "open": 4.4,
      "high": 4.4,
      "low": 4.4,
      "close": 4.4,
      "volume": 0
    },
    {
      "time": "2026-05-07T06:30:00",
      "open": 4.4,
      "high": 4.4,
      "low": 4.4,
      "close": 4.4,
      "volume": 0
    },
    {
      "time": "2026-05-07T06:35:00",
      "open": 4.31,
      "high": 4.31,
      "low": 4.31,
      "close": 4.31,
      "volume": 1
    },
    {
      "time": "2026-05-07T06:40:00",
      "open": 4.31,
      "high": 4.31,
      "low": 4.31,
      "close": 4.31,
      "volume": 0
    },
    {
      "time": "2026-05-07T06:45:00",
      "open": 4.31,
      "high": 4.31,
      "low": 4.27,
      "close": 4.27,
      "volume": 13
    },
    {
      "time": "2026-05-07T06:50:00",
      "open": 4.27,
      "high": 4.27,
      "low": 4.27,
      "close": 4.27,
      "volume": 0
    },
    {
      "time": "2026-05-07T06:55:00",
      "open": 4.27,
      "high": 4.27,
      "low": 4.27,
      "close": 4.27,
      "volume": 0
    },
    {
      "time": "2026-05-07T07:00:00",
      "open": 4.27,
      "high": 4.27,
      "low": 4.27,
      "close": 4.27,
      "volume": 0
    },
    {
      "time": "2026-05-07T07:05:00",
      "open": 4.27,
      "high": 4.27,
      "low": 4.27,
      "close": 4.27,
      "volume": 0
    },
    {
      "time": "2026-05-07T07:10:00",
      "open": 4.27,
      "high": 4.27,
      "low": 4.27,
      "close": 4.27,
      "volume": 0
    },
    {
      "time": "2026-05-07T07:15:00",
      "open": 4.27,
      "high": 4.27,
      "low": 4.27,
      "close": 4.27,
      "volume": 0
    },
    {
      "time": "2026-05-07T07:20:00",
      "open": 4.3109,
      "high": 4.32,
      "low": 4.27,
      "close": 4.32,
      "volume": 14
    },
    {
      "time": "2026-05-07T07:25:00",
      "open": 4.32,
      "high": 4.34,
      "low": 4.32,
      "close": 4.34,
      "volume": 2
    },
    {
      "time": "2026-05-07T07:30:00",
      "open": 4.34,
      "high": 4.34,
      "low": 4.34,
      "close": 4.34,
      "volume": 0
    },
    {
      "time": "2026-05-07T07:35:00",
      "open": 4.4,
      "high": 4.4,
      "low": 4.4,
      "close": 4.4,
      "volume": 10
    },
    {
      "time": "2026-05-07T07:40:00",
      "open": 4.4,
      "high": 4.4,
      "low": 4.4,
      "close": 4.4,
      "volume": 0
    },
    {
      "time": "2026-05-07T07:45:00",
      "open": 4.4,
      "high": 4.4,
      "low": 4.4,
      "close": 4.4,
      "volume": 0
    },
    {
      "time": "2026-05-07T07:50:00",
      "open": 4.39,
      "high": 4.42,
      "low": 4.39,
      "close": 4.39,
      "volume": 31
    },
    {
      "time": "2026-05-07T07:55:00",
      "open": 4.39,
      "high": 4.39,
      "low": 4.39,
      "close": 4.39,
      "volume": 0
    },
    {
      "time": "2026-05-07T08:00:00",
      "open": 4.39,
      "high": 4.39,
      "low": 4.39,
      "close": 4.39,
      "volume": 0
    },
    {
      "time": "2026-05-07T08:05:00",
      "open": 4.39,
      "high": 4.39,
      "low": 4.39,
      "close": 4.39,
      "volume": 0
    },
    {
      "time": "2026-05-07T08:10:00",
      "open": 4.39,
      "high": 4.39,
      "low": 4.39,
      "close": 4.39,
      "volume": 0
    },
    {
      "time": "2026-05-07T08:15:00",
      "open": 4.44,
      "high": 4.45,
      "low": 4.4,
      "close": 4.4,
      "volume": 5
    },
    {
      "time": "2026-05-07T08:20:00",
      "open": 4.43,
      "high": 4.43,
      "low": 4.43,
      "close": 4.43,
      "volume": 5
    },
    {
      "time": "2026-05-07T08:25:00",
      "open": 4.46,
      "high": 4.72,
      "low": 4.46,
      "close": 4.72,
      "volume": 103
    },
    {
      "time": "2026-05-07T08:30:00",
      "open": 4.67,
      "high": 5.2,
      "low": 4.61,
      "close": 4.93,
      "volume": 2781
    },
    {
      "time": "2026-05-07T08:35:00",
      "open": 4.93,
      "high": 5.38,
      "low": 4.93,
      "close": 5.35,
      "volume": 2827
    },
    {
      "time": "2026-05-07T08:40:00",
      "open": 5.34,
      "high": 5.5477,
      "low": 5.28,
      "close": 5.5123,
      "volume": 2542
    },
    {
      "time": "2026-05-07T08:45:00",
      "open": 5.53,
      "high": 5.5498,
      "low": 5.22,
      "close": 5.265,
      "volume": 3247
    },
    {
      "time": "2026-05-07T08:50:00",
      "open": 5.27,
      "high": 5.4,
      "low": 5.2301,
      "close": 5.305,
      "volume": 1732
    },
    {
      "time": "2026-05-07T08:55:00",
      "open": 5.2922,
      "high": 5.3051,
      "low": 5.11,
      "close": 5.1599,
      "volume": 1283
    },
    {
      "time": "2026-05-07T09:00:00",
      "open": 5.16,
      "high": 5.21,
      "low": 5.08,
      "close": 5.125,
      "volume": 650
    },
    {
      "time": "2026-05-07T09:05:00",
      "open": 5.13,
      "high": 5.22,
      "low": 5.11,
      "close": 5.215,
      "volume": 1481
    },
    {
      "time": "2026-05-07T09:10:00",
      "open": 5.22,
      "high": 5.29,
      "low": 5.185,
      "close": 5.2544,
      "volume": 833
    },
    {
      "time": "2026-05-07T09:15:00",
      "open": 5.25,
      "high": 5.3,
      "low": 5.2301,
      "close": 5.255,
      "volume": 569
    },
    {
      "time": "2026-05-07T09:20:00",
      "open": 5.245,
      "high": 5.31,
      "low": 5.21,
      "close": 5.285,
      "volume": 886
    },
    {
      "time": "2026-05-07T09:25:00",
      "open": 5.285,
      "high": 5.39,
      "low": 5.2601,
      "close": 5.365,
      "volume": 727
    },
    {
      "time": "2026-05-07T09:30:00",
      "open": 5.37,
      "high": 5.4,
      "low": 5.3114,
      "close": 5.35,
      "volume": 858
    },
    {
      "time": "2026-05-07T09:35:00",
      "open": 5.345,
      "high": 5.36,
      "low": 5.32,
      "close": 5.345,
      "volume": 330
    },
    {
      "time": "2026-05-07T09:40:00",
      "open": 5.35,
      "high": 5.385,
      "low": 5.31,
      "close": 5.34,
      "volume": 617
    },
    {
      "time": "2026-05-07T09:45:00",
      "open": 5.335,
      "high": 5.335,
      "low": 5.26,
      "close": 5.2714,
      "volume": 371
    },
    {
      "time": "2026-05-07T09:50:00",
      "open": 5.28,
      "high": 5.325,
      "low": 5.25,
      "close": 5.265,
      "volume": 777
    },
    {
      "time": "2026-05-07T09:55:00",
      "open": 5.265,
      "high": 5.325,
      "low": 5.26,
      "close": 5.285,
      "volume": 254
    },
    {
      "time": "2026-05-07T10:00:00",
      "open": 5.285,
      "high": 5.32,
      "low": 5.27,
      "close": 5.285,
      "volume": 436
    },
    {
      "time": "2026-05-07T10:05:00",
      "open": 5.29,
      "high": 5.3,
      "low": 5.26,
      "close": 5.2786,
      "volume": 235
    },
    {
      "time": "2026-05-07T10:10:00",
      "open": 5.2711,
      "high": 5.33,
      "low": 5.205,
      "close": 5.325,
      "volume": 781
    },
    {
      "time": "2026-05-07T10:15:00",
      "open": 5.325,
      "high": 5.36,
      "low": 5.325,
      "close": 5.355,
      "volume": 136
    }
  ]
}